dateutil-stubs/__init__.py
dateutil-stubs/gsheets_connection.py
dateutil_stubs-0.0.4.dist-info/METADATA
dateutil_stubs-0.0.4.dist-info/WHEEL
dateutil_stubs-0.0.4.dist-info/top_level.txt
dateutil_stubs-0.0.4.dist-info/RECORD
